{
  "intro": "A modern CLI for the Gandi v5 REST API — manage your domains and LiveDNS records from the terminal.",
  "features": [
    {
      "title": "Domain management",
      "description": "list registered domains with expiry dates and statuses, renew them for one or more years, and toggle auto-renew."
    },
    {
      "title": "Full DNS control",
      "description": "list, create, update, and delete LiveDNS records with custom TTLs and every standard record type."
    },
    {
      "title": "Web redirects",
      "description": "manage Gandi web forwarding with 301/302 rules straight from the terminal."
    },
    {
      "title": "Permission doctor",
      "description": "gandi doctor reports your token's name, expiry, and scopes, and shows which commands each scope unlocks."
    },
    {
      "title": "PAT authentication",
      "description": "fine-grained, least-privilege Gandi Personal Access Tokens, with graceful guidance when a token is missing or rejected."
    },
    {
      "title": "Script & AI friendly",
      "description": "add --json to any command for structured output, non-zero exit codes on failure, and --yes to skip confirmations."
    }
  ],
  "install": "npm install -g @kud/gandi-cli",
  "examples": [
    "# Domains\ngandi domain list\ngandi domain info example.com\ngandi domain renew example.com --duration 2\n\n# DNS\ngandi dns list example.com\ngandi dns set example.com A www 1.2.3.4 --ttl 300\ngandi dns add example.com A www 5.6.7.8",
    "# Redirects\ngandi redirect add example.com www https://example.org\n\n# Doctor & scripting\ngandi doctor\ngandi dns list example.com --json | jq '.[].name'"
  ]
}